diffTool/__init__.py
diffTool/diffTool.py
pydictdiff-1.0.2.dist-info/licenses/LICENSE
pydictdiff-1.0.2.dist-info/METADATA
pydictdiff-1.0.2.dist-info/WHEEL
pydictdiff-1.0.2.dist-info/top_level.txt
pydictdiff-1.0.2.dist-info/RECORD
