Metadata-Version: 2.4
Name: pydictdiff
Version: 1.0.2
Summary: A Python package to diff two dictionaries
Author-email: Anupam <anupamkrish@duck.com>
License: Copyright (c) 2018 The Python Packaging Authority
Project-URL: Homepage, https://gitlab.com/anupamkrish/pydictdiff
Project-URL: Repository, https://gitlab.com/anupamkrish/pydictdiff
Keywords: diff,dictionary,compare
Requires-Python: >=3.6
License-File: LICENSE
Dynamic: license-file
